cproxy/__init__.py
cproxy/__main__.py
cproxy/cache.py
cproxy/httptools.py
cproxy/options.py
cproxy/proxy.py
cproxy/rules
cproxy/sites_template.db
CProxy-0.1a1.dist-info/LICENSE
CProxy-0.1a1.dist-info/METADATA
CProxy-0.1a1.dist-info/WHEEL
CProxy-0.1a1.dist-info/entry_points.txt
CProxy-0.1a1.dist-info/top_level.txt
CProxy-0.1a1.dist-info/RECORD
