Metadata-Version: 2.1
Name: CProxy
Version: 0.1a1
Summary: A HTTP/HTTPS Caching Proxy
Home-page: https://github.com/coiby/CProxy
Author: Coiby
Author-email: Coiby.Xu@gmail.com
License: GPLv2
Platform: UNKNOWN
Classifier: Topic :: Internet
Classifier: Topic :: Internet :: WWW/HTTP
Classifier: Topic :: Internet :: Proxy Servers
Classifier: Development Status :: 3 - Alpha
Classifier: Environment :: Console
Classifier: Programming Language :: Python :: 3
Classifier: Programming Language :: Python :: 3 :: Only
Classifier: License :: OSI Approved :: GNU General Public License v2 (GPLv2)
Classifier: Operating System :: OS Independent
Requires-Dist: pyOpenSSL
Requires-Dist: brotli
Requires-Dist: chardet
